{"id":"72ceff49-e035-4fcb-a9cf-200a2ecb97c9","created":"2023-06-15T12:21:26.963370Z","redirect":"https://RXkcWPOwSPyATfbZcrRqMfu.vthnJ6sCSaeb.IZnYxkpBtiEHH2myCE6hY0N.1u-1vIWY3Q9","status":"CR","institution_id":"REVOLUT_REVOLT21","agreement":"70bcae78-1050-4a6b-8fcd-b7eccfbb8d0a","reference":"inteligo access 2023.6.15","accounts":[],"user_language":"EN","link":"https://bankaccountdata.gocardless.com/psd2/start/72ceff49-e035-4fcb-a9cf-200a2ecb97c9/REVOLUT_REVOLT21","ssn":null,"account_selection":false,"redirect_immediate":false}